pyloraserver/__init__.py
pyloraserver/applications.py
pyloraserver/device.py
pyloraserver/deviceProfiles.py
pyloraserver/loraserver.py
pyloraserver-0.1.6.dist-info/DESCRIPTION.rst
pyloraserver-0.1.6.dist-info/METADATA
pyloraserver-0.1.6.dist-info/RECORD
pyloraserver-0.1.6.dist-info/WHEEL
pyloraserver-0.1.6.dist-info/metadata.json
pyloraserver-0.1.6.dist-info/top_level.txt
