Metadata-Version: 2.0
Name: pyloraserver
Version: 0.1.6
Summary: A python library for interacting with Loraserver.io.
Home-page: https://github.com/mockingbirdconsulting/pyloraserver
Author: Mockingbird Consulting Ltd
Author-email: info+pyloraserver@mockingbirdconsulting.co.uk
License: UNKNOWN
Platform: UNKNOWN
Classifier: Programming Language :: Python :: 3
Classifier: License :: OSI Approved :: MIT License
Classifier: Operating System :: OS Independent
Requires-Dist: requests (>=2.21.0)
